sumo_simulator/__init__.py
sumo_simulator/car_controller.py
sumo_simulator-0.1.1.dist-info/LICENSE
sumo_simulator-0.1.1.dist-info/METADATA
sumo_simulator-0.1.1.dist-info/WHEEL
sumo_simulator-0.1.1.dist-info/entry_points.txt
sumo_simulator-0.1.1.dist-info/top_level.txt
sumo_simulator-0.1.1.dist-info/RECORD
